gerador_senhas/__init__.py
gerador_senhas/construtor_senha.py
gerador_senhas/verifica_caracteres_senha.py
gerador_senhas-0.0.2.dist-info/METADATA
gerador_senhas-0.0.2.dist-info/WHEEL
gerador_senhas-0.0.2.dist-info/top_level.txt
gerador_senhas-0.0.2.dist-info/RECORD
