Metadata-Version: 2.1
Name: gerador-senhas
Version: 0.0.2
Summary: Pacote para gerar senhas aleatórias contendo números, letras e caracteres especiais.
Home-page: https://github.com/Raf-RM/Bootcamp-Geracao-Tech-Unimed-BH-Ciencia-de-Dados/tree/master/Python-para-cientistas-de-dados/Projeto_Criacao_de_Pacotes_em_Python
Author: Rafael Rodrigues Mateus
Author-email: rafael.r.mateus@gmail.com
License: UNKNOWN
Platform: UNKNOWN
Requires-Python: >=3.8
